Workbook

Sheet Product Backlog
A1: Id | B1: Titulo | C1: Descrição | D1: Categoria | E1: Prioridade | G1: Sprint | H1: Horas Estimadas | I1: Status | J1: Indicador | K1: Comentários
E2: Grau | F2: Classificação
A3: 1 | B3: Cadastro de Comandas | C3: Permite criar e gerenciar comandas individuais para clientes, vinculadas a um número identificador único. | D3: Funcional | E3: 10 | F3: Alta | G3: 1 | H3: 64 | I3: Concluído | J3: Verde | K3: Base essencial para controle de pedidos.
A4: 2 | B4: Registro de Pedidos | C4: Permite registrar itens solicitados por clientes em comandas específicas, detalhando quantidade, descrição e valores dos produtos. | D4: Funcional | E4: 10 | F4: Alta | G4: 1 | H4: 80 | I4: Concluído | J4: Verde | K4: Integra diretamente com as comandas.
A5: 3 | B5: Controle de Pagamento | C5: Centraliza o pagamento das comandas no caixa, registrando métodos de pagamento (dinheiro, cartão) e oferecendo cálculo do total devido. | D5: Funcional | E5: 10 | F5: Média | G5: 2 | H5: 88 | I5: Em andamento | J5: Amarelo | K5: Fundamental para a saída controlada do cliente.
A6: 4 | B6: Controle de Saída | C6: Permite que o porteiro consulte o pagamento das comandas antes de liberar a saída do cliente, garantindo a integridade do processo de pagamento. | D6: Funcional | E6: 10 | F6: Média | G6: 2 | H6: 72 | I6: Em andamento | J6: Verde | K6: Relacionado diretamente ao fechamento de contas.
A7: 5 | B7: Cálculo da Consumação Mínima | C7: Automatiza o cálculo e a verificação do cumprimento da consumação mínima exigida, incluindo o valor pendente na conta quando necessário. | D7: Funcional | E7: 9 | F7: Média | G7: 3 | H7: 56 | I7: Em andamento | J7: Vermelho | K7: Regra de negócio essencial para o boteco.
A8: 6 | B8: Cadastro de Produtos | C8: Permite registrar e atualizar os produtos disponíveis no cardápio, incluindo nome, preço e categoria (bebidas, petiscos, etc.). | D8: Funcional | E8: 8 | F8: Média | G8: 3 | H8: 96 | I8: Em andamento | J8: Verde | K8: Base de dados para pedidos e estoque.
A9: 7 | B9: Controle de Estoque | C9: Reduz automaticamente o estoque conforme os pedidos são realizados e emite alertas para reposição quando o nível mínimo for atingido. | D9: Funcional | E9: 8 | F9: Média | G9: 4 | H9: 64 | I9: Em andamento | J9: Verde | K9: Controle para evitar rupturas no serviço.
A10: 8 | B10: Relatórios de Vendas | C10: Gera relatórios diários, semanais e mensais sobre o volume de vendas, itens mais vendidos e faturamento total. | D10: Negócio | E10: 7 | F10: Média | G10: 5 | H10: 88 | I10: Em andamento | J10: Verde | K10: Auxilia na análise de desempenho financeiro.
A11: 9 | B11: Gerenciamento de Acesso | C11: Implementa sistema de login com permissões baseadas em perfil (garçom, caixa, gerente e administrador), garantindo segurança no uso do sistema. | D11: Funcional | E11: 7 | F11: Média | G11: 4 | H11: 64 | I11: Em andamento | J11: Verde | K11: Controle de acesso diferenciado por função.
A12: 10 | B12: Relatório de Consumação | C12: Gera um relatório consolidado das comandas que não atingiram a consumação mínima e exibe o valor adicional incluído nos | D12: Negócio | E12: 6 | F12: Média | G12: 5 | H12: 72 | I12: Em andamento | J12: Amarelo | K12: Facilitador para controle de regras internas.
A13: 11 | B13: Dashboard de Gestão | C13: Tela principal com indicadores visuais para acompanhar comandas abertas, volume de vendas em tempo real e situação do estoque. | D13: Funcional | E13: 6 | F13: Média | G13: 6 | H13: 40 | I13: Em andamento | J13: Verde | K13: Recurso para tomada de decisões rápidas.
A14: 12 | B14: Fechamento Diário | C14: Facilita o fechamento do caixa ao final do dia, consolidando as informações de vendas, pagamentos e estoque. | D14: Funcional | E14: 6 | F14: Média | G14: 6 | H14: 56 | I14: Em andamento | J14: Verde | K14: Relacionado aos relatórios e ao controle do caixa

Sheet Sprint Backlog
A1: C | B1: Período do Sprint | C1: 45627 | D1: a | E1: 45717 | L1: Referência | M1: =TODAY() -> 45777 | N1: Horas Sprint | O1: =SUM(F4:F15) -> 800
A2: Id | B2: Titulo | C2: Horas Estimadas | D2: Início | E2: Fim | F2: Horas Efetivas | G2: Status | H2: Indicador | I2: Comentários | L2: Planejado | N2: Realizado
L3: Horas | M3: Restante | N3: Horas | O3: Dif
A4: 1 | B4: =IF(A4="","",VLOOKUP(A4,'Product Backlog'!A3:K14,2,FALSE)) -> Cadastro de Comandas | C4: =IF(A4="","",VLOOKUP(A4,'Product Backlog'!A3:K14,8,FALSE)) -> 64 | D4: 45627 | E4: 45631 | F4: =IF(A4="","",(E4-D4+1)*parametros!G2) -> 40 | G4: Concluído | H4: Verde | J4: 45627 | K4: =C1 -> 45627 | L4: Total | M4: =SUM(L5:L15) -> 856 | O4: =SUM(N5:N15) -> 768
A5: 2 | B5: =IF(A5="","",VLOOKUP(A5,'Product Backlog'!A4:K15,2,FALSE)) -> Registro de Pedidos | C5: =IF(A5="","",VLOOKUP(A5,'Product Backlog'!A4:K15,8,FALSE)) -> 80 | D5: 45632 | E5: 45635 | F5: =IF(A5="","",(E5-D5+1)*parametros!G2) -> 32 | G5: Concluído | H5: Verde | J5: 45636 | K5: 45630 | L5: =C4 -> 64 | M5: =IF(L5="","",$O$1-L5) -> 736 | N5: =F4 -> 40 | O5: =IF(A4="","",O1-N5) -> 760
A6: 3 | B6: =IF(A6="","",VLOOKUP(A6,'Product Backlog'!A5:K16,2,FALSE)) -> Controle de Pagamento | C6: =IF(A6="","",VLOOKUP(A6,'Product Backlog'!A5:K16,8,FALSE)) -> 88 | D6: 45636 | E6: 45645 | F6: =IF(A6="","",(E6-D6+1)*parametros!G2) -> 80 | G6: Em andamento | H6: Amarelo | J6: 45646 | K6: =K5+12 -> 45642 | L6: =C5 -> 80 | M6: =IF(L6="","",M5-L6) -> 656 | N6: =F5 -> 32 | O6: =IF(A5="","",O5-N6) -> 728
A7: 4 | B7: =IF(A7="","",VLOOKUP(A7,'Product Backlog'!A6:K17,2,FALSE)) -> Controle de Saída | C7: =IF(A7="","",VLOOKUP(A7,'Product Backlog'!A6:K17,8,FALSE)) -> 72 | D7: 45645 | E7: 45653 | F7: =IF(A7="","",(E7-D7+1)*parametros!G2) -> 72 | G7: Em andamento | H7: Verde | J7: 45656 | K7: =K6+12 -> 45654 | L7: =C6 -> 88 | M7: =IF(L7="","",M6-L7) -> 568 | N7: =F6 -> 80 | O7: =IF(A6="","",O6-N7) -> 648
A8: 5 | B8: =IF(A8="","",VLOOKUP(A8,'Product Backlog'!A7:K18,2,FALSE)) -> Cálculo da Consumação Mínima | C8: 128 | D8: 45653 | E8: 45670 | F8: =IF(A9="","",(E8-D8+1)*parametros!G2) -> 144 | G8: Em andamento | H8: Vermelho | J8: 45667 | K8: =K7+10 -> 45664 | L8: =C7 -> 72 | M8: =IF(L8="","",M7-L8) -> 496 | N8: =F7 -> 72 | O8: =IF(A7="","",O7-N8) -> 576
A9: 6 | B9: =IF(A9="","",VLOOKUP(A9,'Product Backlog'!A8:K19,2,FALSE)) -> Cadastro de Produtos | C9: =IF(A9="","",VLOOKUP(A9,'Product Backlog'!A8:K19,8,FALSE)) -> 96 | D9: 45670 | E9: 45679 | F9: =IF(A9="","",(E9-D9+1)*parametros!G2) -> 80 | G9: Em andamento | H9: Verde | J9: 45677 | K9: =K8+12 -> 45676 | L9: =C8 -> 128 | M9: =IF(L9="","",M8-L9) -> 368 | N9: =F8 -> 144 | O9: =IF(A8="","",O8-N9) -> 432
A10: 7 | B10: =IF(A10="","",VLOOKUP(A10,'Product Backlog'!A9:K20,2,FALSE)) -> Controle de Estoque | C10: =IF(A10="","",VLOOKUP(A10,'Product Backlog'!A9:K20,8,FALSE)) -> 64 | D10: 45679 | E10: 45686 | F10: =IF(A10="","",(E10-D10+1)*parametros!G2) -> 64 | G10: Em andamento | H10: Verde | J10: 45687 | K10: =K9+10 -> 45686 | L10: =C9 -> 96 | M10: =IF(L10="","",M9-L10) -> 272 | N10: =F9 -> 80 | O10: =IF(A9="","",O9-N10) -> 352
A11: 8 | B11: =IF(A11="","",VLOOKUP(A11,'Product Backlog'!A10:K21,2,FALSE)) -> Relatórios de Vendas | C11: =IF(A11="","",VLOOKUP(A11,'Product Backlog'!A10:K21,8,FALSE)) -> 88 | D11: 45686 | E11: 45695 | F11: =IF(A11="","",(E11-D11+1)*parametros!G2) -> 80 | G11: Em andamento | H11: Verde | J11: 45698 | K11: =K10+10 -> 45696 | L11: =C10 -> 64 | M11: =IF(L11="","",M10-L11) -> 208 | N11: =F10 -> 64 | O11: =IF(A10="","",O10-N11) -> 288
A12: 9 | B12: =IF(A12="","",VLOOKUP(A12,'Product Backlog'!A11:K22,2,FALSE)) -> Gerenciamento de Acesso | C12: =IF(A12="","",VLOOKUP(A12,'Product Backlog'!A11:K22,8,FALSE)) -> 64 | D12: 45695 | E12: 45701 | F12: =IF(A12="","",(E12-D12+1)*parametros!G2) -> 56 | G12: Em andamento | H12: Verde | J12: 45708 | K12: =K11+10 -> 45706 | L12: =C11 -> 88 | M12: =IF(L12="","",M11-L12) -> 120 | N12: =F11 -> 80 | O12: =IF(A11="","",O11-N12) -> 208
A13: 10 | B13: =IF(A13="","",VLOOKUP(A13,'Product Backlog'!A12:K23,2,FALSE)) -> Relatório de Consumação | C13: =IF(A13="","",VLOOKUP(A13,'Product Backlog'!A12:K23,8,FALSE)) -> 72 | D13: 45701 | E13: 45711 | F13: =IF(A13="","",(E13-D13+1)*parametros!G2) -> 88 | G13: Em andamento | H13: Amarelo | J13: 45717 | K13: =K12+8 -> 45714 | L13: =C12 -> 64 | M13: =IF(L13="","",M12-L13) -> 56 | N13: =F12 -> 56 | O13: =IF(A12="","",O12-N13) -> 152
A14: 11 | B14: =IF(A14="","",VLOOKUP(A14,'Product Backlog'!A13:K24,2,FALSE)) -> Dashboard de Gestão | C14: =IF(A14="","",VLOOKUP(A14,'Product Backlog'!A13:K24,8,FALSE)) -> 40 | D14: 45711 | E14: 45714 | F14: =IF(A14="","",(E14-D14+1)*parametros!G2) -> 32 | G14: Em andamento | H14: Verde | K14: =K13+1 -> 45715 | L14: =C13 -> 72 | M14: =IF(L14="","",M13-L14) -> -16 | N14: =F13 -> 88 | O14: =IF(A13="","",O13-N14) -> 64
A15: 12 | B15: =IF(A15="","",VLOOKUP(A15,'Product Backlog'!A14:K25,2,FALSE)) -> Fechamento Diário | C15: =IF(A15="","",VLOOKUP(A15,'Product Backlog'!A14:K25,8,FALSE)) -> 56 | D15: 45714 | E15: 45717 | F15: =IF(A15="","",(E15-D15+1)*parametros!G2) -> 32 | G15: Em andamento | H15: Verde | K15: 45352 | L15: =C14 -> 40 | M15: =IF(L15="","",M14-L15) -> -56 | N15: =F14 -> 32 | O15: =IF(A14="","",O14-N15) -> 32

Sheet BurndownChart Geral
C1: Planejado | D1: Efetivo | E1: Planejado | F1: Efetivo
B2: 0 | C2: 120 | D2: =SUM(D3:D12) -> 100 | E2: =C2 -> 120 | F2: =E2 -> 120
B3: 1 | C3: 12 | D3: 8 | E3: =IF(C3="","",E2-C3) -> 108 | F3: =IF(D3="","",F2-D3) -> 112
B4: 2 | C4: 32 | D4: 32 | E4: =IF(C4="","",E3-C4) -> 76 | F4: =IF(D4="","",F3-D4) -> 80
B5: 3 | C5: 16 | D5: 4 | E5: =IF(C5="","",E4-C5) -> 60 | F5: =IF(D5="","",F4-D5) -> 76
B6: 4 | C6: 8 | D6: 0 | E6: =IF(C6="","",E5-C6) -> 52 | F6: =IF(D6="","",F5-D6) -> 76
B7: 5 | C7: 4 | D7: 24 | E7: =IF(C7="","",E6-C7) -> 48 | F7: =IF(D7="","",F6-D7) -> 52
B8: 6 | C8: 16 | D8: 4 | E8: =IF(C8="","",E7-C8) -> 32 | F8: =IF(D8="","",F7-D8) -> 48
B9: 7 | C9: 8 | D9: 4 | E9: =IF(C9="","",E8-C9) -> 24 | F9: =IF(D9="","",F8-D9) -> 44
B10: 8 | C10: 8 | D10: 8 | E10: =IF(C10="","",E9-C10) -> 16 | F10: =IF(D10="","",F9-D10) -> 36
B11: 9 | C11: 8 | D11: 0 | E11: =IF(C11="","",E10-C11) -> 8 | F11: =IF(D11="","",F10-D11) -> 36
B12: 10 | C12: 8 | D12: 16 | E12: =IF(C12="","",E11-C12) -> 0 | F12: =IF(D12="","",F11-D12) -> 20
D14: 8
D15: 32
D16: 4
D17: 0
D18: 24
D19: 4
D20: 4
D21: 8
D22: 0

Sheet parametros
A1: Categoria | B1: Classificação | D1: Indicador | E1: Status | F1: Grau | G1: Produtividade
A2: Requisitos | B2: Baixa | C2: 8 a 10 | D2: Verde | E2: Criado | F2: 0 | G2: 8
A3: Especificação | B3: Média | C3: 4 a 7 | D3: Amarelo | E3: Em andamento | F3: 1
A4: Planejamento | B4: Alta | C4: 0 e 3 | D4: Vermelho | E4: Cancelado | F4: 2
A5: Software | E5: Suspenso | F5: 3
A6: Recursos | E6: Concluído | F6: 4
E7: Agregado | F7: 5
F8: 6
F9: 7
F10: 8
F11: 9
F12: 10
